{
  "version": "6",
  "dialect": "sqlite",
  "id": "5bd379d8-71ab-4a9f-818e-a311fca72f32",
  "prevId": "00000000-0000-0000-0000-000000000000",
  "tables": {
    "sync_status": {
      "name": "sync_status",
      "columns": {
        "account_id": {
          "name": "account_id",
          "type": "text",
          "primaryKey": true,
          "notNull": true,
          "autoincrement": false
        },
        "last_sync": {
          "name": "last_sync",
          "type": "integer",
          "primaryKey": false,
          "notNull": true,
          "autoincrement": false
        },
        "total_trades": {
          "name": "total_trades",
          "type": "integer",
          "primaryKey": false,
          "notNull": true,
          "autoincrement": false
        }
      },
      "indexes": {},
      "foreignKeys": {},
      "compositePrimaryKeys": {},
      "uniqueConstraints": {},
      "checkConstraints": {}
    },
    "trade_history": {
      "name": "trade_history",
      "columns": {
        "id": {
          "name": "id",
          "type": "integer",
          "primaryKey": true,
          "notNull": true,
          "autoincrement": true
        },
        "account_id": {
          "name": "account_id",
          "type": "text",
          "primaryKey": false,
          "notNull": true,
          "autoincrement": false
        },
        "pos_id": {
          "name": "pos_id",
          "type": "text",
          "primaryKey": false,
          "notNull": true,
          "autoincrement": false
        },
        "token_c": {
          "name": "token_c",
          "type": "text",
          "primaryKey": false,
          "notNull": true,
          "autoincrement": false
        },
        "token_d": {
          "name": "token_d",
          "type": "text",
          "primaryKey": false,
          "notNull": true,
          "autoincrement": false
        },
        "token_p": {
          "name": "token_p",
          "type": "text",
          "primaryKey": false,
          "notNull": true,
          "autoincrement": false
        },
        "trend": {
          "name": "trend",
          "type": "text",
          "primaryKey": false,
          "notNull": true,
          "autoincrement": false
        },
        "entry_price": {
          "name": "entry_price",
          "type": "text",
          "primaryKey": false,
          "notNull": true,
          "autoincrement": false
        },
        "exit_price": {
          "name": "exit_price",
          "type": "text",
          "primaryKey": false,
          "notNull": true,
          "autoincrement": false
        },
        "amount_c": {
          "name": "amount_c",
          "type": "text",
          "primaryKey": false,
          "notNull": true,
          "autoincrement": false
        },
        "amount_d": {
          "name": "amount_d",
          "type": "text",
          "primaryKey": false,
          "notNull": true,
          "autoincrement": false
        },
        "amount_p": {
          "name": "amount_p",
          "type": "text",
          "primaryKey": false,
          "notNull": true,
          "autoincrement": false
        },
        "pnl": {
          "name": "pnl",
          "type": "real",
          "primaryKey": false,
          "notNull": true,
          "autoincrement": false
        },
        "open_timestamp": {
          "name": "open_timestamp",
          "type": "integer",
          "primaryKey": false,
          "notNull": true,
          "autoincrement": false
        },
        "close_timestamp": {
          "name": "close_timestamp",
          "type": "integer",
          "primaryKey": false,
          "notNull": true,
          "autoincrement": false
        },
        "close_type": {
          "name": "close_type",
          "type": "text",
          "primaryKey": false,
          "notNull": true,
          "autoincrement": false
        },
        "fee": {
          "name": "fee",
          "type": "text",
          "primaryKey": false,
          "notNull": true,
          "autoincrement": false
        },
        "updated_at": {
          "name": "updated_at",
          "type": "integer",
          "primaryKey": false,
          "notNull": true,
          "autoincrement": false
        }
      },
      "indexes": {
        "trade_history_pos_id_unique": {
          "name": "trade_history_pos_id_unique",
          "columns": [
            "pos_id"
          ],
          "isUnique": true
        },
        "idx_account_id": {
          "name": "idx_account_id",
          "columns": [
            "account_id"
          ],
          "isUnique": false
        },
        "idx_close_timestamp": {
          "name": "idx_close_timestamp",
          "columns": [
            "close_timestamp"
          ],
          "isUnique": false
        }
      },
      "foreignKeys": {},
      "compositePrimaryKeys": {},
      "uniqueConstraints": {},
      "checkConstraints": {}
    }
  },
  "views": {},
  "enums": {},
  "_meta": {
    "schemas": {},
    "tables": {},
    "columns": {}
  },
  "internal": {
    "indexes": {}
  }
}